chi1chi2/__init__.py
chi1chi2/analyze.py
chi1chi2/calculate_effective_d.py
chi1chi2/from_cif.py
chi1chi2/from_crystal.py
chi1chi2/from_fra.py
chi1chi2/input_preparator.py
chi1chi2/main.py
chi1chi2/charges/__init__.py
chi1chi2/cif/__init__.py
chi1chi2/cif/cif_parser.py
chi1chi2/core/__init__.py
chi1chi2/core/bulk_property.py
chi1chi2/core/property.py
chi1chi2/core/property_reader.py
chi1chi2/crystal_support/__init__.py
chi1chi2/crystal_support/crystal_reader.py
chi1chi2/helpers/__init__.py
chi1chi2/helpers/calc_pol.py
chi1chi2/helpers/read_g09.py
chi1chi2/helpers/scale_props.py
chi1chi2/input/__init__.py
chi1chi2/input/input_preparator.py
chi1chi2/periodic_table/__init__.py
chi1chi2/periodic_table/periodic_table.py
chi1chi2/periodic_table/ptable.csv
chi1chi2/utils/__init__.py
chi1chi2/utils/constants.py
chi1chi2/utils/molecule.py
chi1chi2/utils/molecule_reader_writer.py
chi1chi2/utils/molecule_reorderer.py
tests/__init__.py
tests/analysis/__init__.py
tests/analysis/test_analysis.py
tests/cif/__init__.py
tests/cif/test_cif_parser.py
tests/core/__init__.py
tests/core/test_bulk_property.py
tests/core/test_distributed.py
tests/core/test_lorentz.py
tests/core/test_property.py
tests/core/test_property_reader.py
tests/crystal_support/__init__.py
tests/crystal_support/test_crystal_reader.py
tests/helpers/__init__.py
tests/helpers/test_calc_pol.py
tests/helpers/test_read_g09.py
tests/helpers/test_scale_props.py
tests/input/__init__.py
tests/input/test_input_preparator.py
tests/input/test_symmop_transformation.py
tests/input/test_symmop_translator.py
tests/molecule/__init__.py
tests/molecule/test_molecule.py
tests/molecule/test_read_write_molecule.py
tests/snapshot/__init__.py
tests/snapshot/test_additional.py
tests/snapshot/test_dast.py
tests/snapshot/test_mna.py
tests/snapshot/test_runner.py
chi1chi2-0.9.5.dist-info/LICENSE
chi1chi2-0.9.5.dist-info/METADATA
chi1chi2-0.9.5.dist-info/WHEEL
chi1chi2-0.9.5.dist-info/entry_points.txt
chi1chi2-0.9.5.dist-info/top_level.txt
chi1chi2-0.9.5.dist-info/RECORD
