Metadata-Version: 2.1
Name: chi1chi2
Version: 0.9.5
Summary: set of scripts for calculating linear and nonlinear optical properties of organic crystals
Home-page: https://bitbucket.org/tomeks86/chi1chi2
Author: Tomasz Seidler
Author-email: tomasz.z.seidler@gmail.com
License: MIT License
Platform: UNKNOWN
Classifier: Development Status :: 3 - Alpha
Classifier: Environment :: Console
Classifier: Intended Audience :: Science/Research
Classifier: License :: OSI Approved :: MIT License
Classifier: Natural Language :: English
Classifier: Operating System :: POSIX :: Linux
Classifier: Programming Language :: Python :: 3 :: Only
Classifier: Programming Language :: Fortran
Classifier: Topic :: Scientific/Engineering :: Physics
Classifier: Topic :: Scientific/Engineering :: Chemistry
Requires-Dist: numpy (==1.21.5)
Requires-Dist: PyCifRW (==4.4.3)
